teardown/__init__.py
teardown/_teardown.py
teardown/plugin.py
pytest_teardown-2.1.0.dist-info/METADATA
pytest_teardown-2.1.0.dist-info/WHEEL
pytest_teardown-2.1.0.dist-info/entry_points.txt
pytest_teardown-2.1.0.dist-info/RECORD
