Metadata-Version: 2.3
Name: pytest-teardown
Version: 2.1.0
Summary: 
Author: Albert Safin
Requires-Python: >=3.8,<4.0
Classifier: Programming Language :: Python :: 3
Classifier: Programming Language :: Python :: 3.8
Classifier: Programming Language :: Python :: 3.9
Classifier: Programming Language :: Python :: 3.10
Classifier: Programming Language :: Python :: 3.11
Classifier: Programming Language :: Python :: 3.12
Classifier: Programming Language :: Python :: 3.13
Requires-Dist: pytest (>=7.4.1,<9.0.0)
Requires-Dist: simple-singleton (>=2.0.0,<3.0.0)
